example/__init__.py
example/manage.py
example/dj/__init__.py
example/dj/urls.py
example/dj/wsgi.py
example/dj/apps/__init__.py
example/dj/apps/app/__init__.py
example/dj/apps/app/models.py
example/dj/apps/app/resource.py
example/dj/apps/app/serializable.py
example/dj/apps/app/dynamo/__init__.py
example/dj/apps/app/dynamo/models.py
example/dj/apps/app/dynamo/resource.py
example/dj/apps/app/elasticsearch/__init__.py
example/dj/apps/app/elasticsearch/models.py
example/dj/apps/app/elasticsearch/resource.py
example/dj/apps/app/migrations/0001_initial.py
example/dj/apps/app/migrations/0002_user_manual_created_date.py
example/dj/apps/app/migrations/0003_auto_20170729_2305.py
example/dj/apps/app/migrations/0004_issue_tags.py
example/dj/apps/app/migrations/__init__.py
example/dj/apps/app/tests/__init__.py
example/dj/apps/app/tests/compatibility.py
example/dj/apps/app/tests/cors.py
example/dj/apps/app/tests/dynamo.py
example/dj/apps/app/tests/elasticsearch.py
example/dj/apps/app/tests/extra_resource.py
example/dj/apps/app/tests/factories.py
example/dj/apps/app/tests/fields.py
example/dj/apps/app/tests/fieldsets.py
example/dj/apps/app/tests/filter.py
example/dj/apps/app/tests/order.py
example/dj/apps/app/tests/serializer.py
example/dj/apps/app/tests/standard_operations.py
example/dj/apps/app/tests/test_case.py
example/dj/settings/__init__.py
example/dj/settings/base.py
example/dj/settings/settings.py
pyston/__init__.py
pyston/cache.py
pyston/conf.py
pyston/data_processor.py
pyston/exception.py
pyston/metamodel.py
pyston/models.py
pyston/paginator.py
pyston/patch.py
pyston/resource.py
pyston/response.py
pyston/serializer.py
pyston/validators.py
pyston/version.py
pyston/contrib/__init__.py
pyston/contrib/dynamo/__init__.py
pyston/contrib/dynamo/filter.py
pyston/contrib/dynamo/order.py
pyston/contrib/dynamo/paginator.py
pyston/contrib/dynamo/resource.py
pyston/contrib/elasticsearch/__init__.py
pyston/contrib/elasticsearch/filters.py
pyston/contrib/elasticsearch/order.py
skip_django_pyston-2.17.1.dist-info/licenses/AUTHORS.txt
skip_django_pyston-2.17.1.dist-info/licenses/LICENSE
skip_django_pyston-2.17.1.dist-info/METADATA
skip_django_pyston-2.17.1.dist-info/WHEEL
skip_django_pyston-2.17.1.dist-info/top_level.txt
skip_django_pyston-2.17.1.dist-info/RECORD
