Metadata-Version: 2.4
Name: skip-django-pyston
Version: 2.17.1
Summary: Pyston is a Django mini-framework creating APIs.
Home-page: https://github.com/skip-pay/django-pyston
Author: Lubos Matl
Author-email: matllubos@gmail.com
License: BSD
Classifier: Development Status :: 3 - Alpha
Classifier: Framework :: Django
Classifier: Intended Audience :: Developers
Classifier: License :: OSI Approved :: BSD License
Classifier: Operating System :: OS Independent
Classifier: Programming Language :: Python
Classifier: Topic :: Internet :: WWW/HTTP
License-File: LICENSE
License-File: AUTHORS.txt
Requires-Dist: django>=4.2
Requires-Dist: defusedxml>=0.6.0
Requires-Dist: pyparsing==2.4.7
Requires-Dist: python-mimeparse>=1.6.0
Requires-Dist: skip-django-chamber>=0.7.2
Requires-Dist: python-magic>=0.4.27
Dynamic: author
Dynamic: author-email
Dynamic: classifier
Dynamic: home-page
Dynamic: license
Dynamic: license-file
Dynamic: requires-dist
Dynamic: summary
